miner/__init__.py
miner/utils.cpython-37m-darwin.so
mi_ner-0.6.1.dist-info/LICENSE
mi_ner-0.6.1.dist-info/METADATA
mi_ner-0.6.1.dist-info/WHEEL
mi_ner-0.6.1.dist-info/top_level.txt
mi_ner-0.6.1.dist-info/RECORD
