Metadata-Version: 2.1
Name: mi-ner
Version: 0.6.1
Summary: A python library for named entity recognition evaluation
Home-page: https://github.com/Andolab/miNER
Author: Ryuya Ikeda
Author-email: rikeda71@gmail.com
License: MIT
Keywords: named entity recognition,nlp,natural language processing
Platform: UNKNOWN
Classifier: License :: OSI Approved :: MIT License
Classifier: Programming Language :: Python :: 3.6
Classifier: Programming Language :: Python :: 3.7
Classifier: Topic :: Text Processing
Requires-Dist: cython
